Workbook

Sheet Summary
A1: Vehicle Conduct Review - Evidence Pack
A2: Vehicle: 'king Javiar' (Raptor, BlackVue via Fleeta Cloud). Driver: Javiar Cartledge. Prepared 06/09/2026. CONFIDENTIAL - HR file.
A4: Item | B4: Finding / status | C4: Source | D4: Next action
A5: Fri 28 Aug & Sat 29 Aug - grey days in Fleeta | B5: 0 jobs allocated to Javiar either day (other techs had 5 jobs on 28/08). Zero camera events is consistent with the vehicle not being driven. Not evidence of a fault or of concealment. | C5: ServiceM8 schedule, Fleeta calendar | D5: Close out. Optional: Fleeta Trip History 28-29/08 to confirm zero ignition.
A6: Fri 4 Sep - 40+ triggered events | B6: 7 stops, ~180 km (estimate), Sunnybank > Fortitude Valley > Thornlands > Murarrie > Morayfield > Narangba > Murrumba Downs. Long motorway legs. Arrived 63 min early to last job. One 33-second non-customer stop (Narangba, 'drop cash', staff address). | C6: ServiceM8 diaries + Fleeta | D6: Match every event to a leg on the Timeline sheet. Download all Driving Impact clips.
A7: Sat 5 Sep - 17 events 07:03-08:34 | B7: Chapel Hill job (booked 08:00): travel clock started 05:19, checked out 07:46 with 4 seconds on site, job not done. Then bed bug job South Brisbane 08:11-08:20 (9 min, 1 mandatory task skipped). Parked 08:34 (Parking Impact). Reported sick by ~11:07; Jason took his 11:15 job. | C7: ServiceM8 diaries + Fleeta | D7: PRIORITY: Fleeta Trip History 05:00-08:40 on 05/09 to account for the 2h27m. Download all 17 clips.
A8: Cabin audio | B8: Unknown until a clip is opened. Qld Invasion of Privacy Act 1971 s43: recording a private conversation you are not party to is an offence. If audio is ON, do NOT listen, share or rely on it until a lawyer has advised. Treat it as a liability, not an asset. | C8: BlackVue config | D8: Check camera audio setting. Get legal advice before any use. Consider turning audio OFF fleet-wide with written notice.
A9: SD card | B9: August already overwritten. September continuous footage still on card but cycling. Cloud only holds trigger clips, the card holds the footage BETWEEN triggers (the real driving picture). | C9: BlackVue SD picker | D9: Pull the card Mon 07/09 before the vehicle moves. Image it, hash it, bag it. Fit a fresh formatted card.
A10: Passenger | B10: Identity, role (staff / trainee / customer / other) and whether they have made a complaint are not yet on file. This decides which process runs: driving/WHS conduct, or harassment complaint (positive duty), or both. | C10: Jason | D10: Confirm before the allegations letter is drafted. If a complaint exists, the complainant's account comes first.
A11: Process risk | B11: Driver shares the owner's surname. Perceived conflict of interest in any disciplinary outcome. Small business (<15 staff): Small Business Fair Dismissal Code applies but procedural fairness is still required. | C11: Staff list | D11: Have an independent person (external HR adviser) run the meeting and record it.
A13: Event counts (live from Event_Log sheet)
A14: Date | B14: Total events | C14: Driving Impact | D14: Hard Braking | E14: Hard Cornering | F14: Hard Acceleration | G14: Parking Impact
A15: 46262 | B15: =COUNTIF(Event_Log!$A:$A,A15) | C15: =COUNTIFS(Event_Log!$A:$A,A15,Event_Log!$C:$C,"Driving Impact") | D15: =COUNTIFS(Event_Log!$A:$A,A15,Event_Log!$C:$C,"Hard Braking") | E15: =COUNTIFS(Event_Log!$A:$A,A15,Event_Log!$C:$C,"Hard Cornering") | F15: =COUNTIFS(Event_Log!$A:$A,A15,Event_Log!$C:$C,"Hard Acceleration") | G15: =COUNTIFS(Event_Log!$A:$A,A15,Event_Log!$C:$C,"Parking Impact")
A16: 46263 | B16: =COUNTIF(Event_Log!$A:$A,A16) | C16: =COUNTIFS(Event_Log!$A:$A,A16,Event_Log!$C:$C,"Driving Impact") | D16: =COUNTIFS(Event_Log!$A:$A,A16,Event_Log!$C:$C,"Hard Braking") | E16: =COUNTIFS(Event_Log!$A:$A,A16,Event_Log!$C:$C,"Hard Cornering") | F16: =COUNTIFS(Event_Log!$A:$A,A16,Event_Log!$C:$C,"Hard Acceleration") | G16: =COUNTIFS(Event_Log!$A:$A,A16,Event_Log!$C:$C,"Parking Impact")
A17: 46269 | B17: =COUNTIF(Event_Log!$A:$A,A17) | C17: =COUNTIFS(Event_Log!$A:$A,A17,Event_Log!$C:$C,"Driving Impact") | D17: =COUNTIFS(Event_Log!$A:$A,A17,Event_Log!$C:$C,"Hard Braking") | E17: =COUNTIFS(Event_Log!$A:$A,A17,Event_Log!$C:$C,"Hard Cornering") | F17: =COUNTIFS(Event_Log!$A:$A,A17,Event_Log!$C:$C,"Hard Acceleration") | G17: =COUNTIFS(Event_Log!$A:$A,A17,Event_Log!$C:$C,"Parking Impact")
A18: 46270 | B18: =COUNTIF(Event_Log!$A:$A,A18) | C18: =COUNTIFS(Event_Log!$A:$A,A18,Event_Log!$C:$C,"Driving Impact") | D18: =COUNTIFS(Event_Log!$A:$A,A18,Event_Log!$C:$C,"Hard Braking") | E18: =COUNTIFS(Event_Log!$A:$A,A18,Event_Log!$C:$C,"Hard Cornering") | F18: =COUNTIFS(Event_Log!$A:$A,A18,Event_Log!$C:$C,"Hard Acceleration") | G18: =COUNTIFS(Event_Log!$A:$A,A18,Event_Log!$C:$C,"Parking Impact")
A19: Counts fill in as you enter events on Event_Log. Fleeta showed ~40+ on 04/09 and 17 (07:03-08:34) on 05/09 at first look.

Sheet Timeline
A1: Driver timeline from ServiceM8 (all times local AEST, hh:mm:ss). Camera-event column counts Event_Log rows falling in each leg's travel window.
A2: Date | B2: Leg | C2: To (job / suburb) | D2: Job # | E2: Booked | F2: On-the-way SMS | G2: Travel start (derived) | H2: Check-in | I2: Check-out | J2: Travel time | K2: On-site time | L2: Camera events in travel window | M2: Flag | N2: Note (source: ServiceM8 diary)
A3: 46269 | B3: 1 | C3: Sunnybank - commercial food premises | D3: 24795 | E3: 0.27083333 | F3: 0.25486111 | G3: 0.25471065 | H3: 0.26875 | I3: 0.29722222 | J3: 0.014039352 | K3: 0.02849537 | L3: =COUNTIFS(Event_Log!$A:$A,A3,Event_Log!$B:$B,">="&G3,Event_Log!$B:$B,"<="&H3) | N3: On-the-way SMS sent twice (06:07, 06:23). Booking note: someone on site from 06:30.
A4: 46269 | B4: 2 | C4: Fortitude Valley - German cockroach | D4: 24316 | E4: 0.35416667 | F4: 0.32569444 | G4: 0.32604167 | H4: 0.33402778 | I4: 0.37152778 | J4: 0.008125 | K4: 0.037534722 | L4: =COUNTIFS(Event_Log!$A:$A,A4,Event_Log!$B:$B,">="&G4,Event_Log!$B:$B,"<="&H4) | M4: Gap | N4: 07:08-07:49 (41 min) between check-out and travel start is unaccounted. 06:50 SMS to client 'technician delayed on a previous job' was sent while still at Sunnybank.
A5: 46269 | B5: 3 | C5: Thornlands - termite inspection | D5: 24654 | E5: 0.41666667 | F5: 0.37222222 | G5: 0.3715625 | H5: 0.40416667 | I5: 0.42430556 | J5: 0.032604167 | K5: 0.02025463 | L5: =COUNTIFS(Event_Log!$A:$A,A5,Event_Log!$B:$B,">="&G5,Event_Log!$B:$B,"<="&H5) | M5: Long leg | N5: Inner city to bayside, ~32 km, motorway. 48-min ETA quoted.
A6: 46269 | B6: 4 | C6: Murarrie - general pest | D6: 24740 | E6: 0.47916667 | F6: 0.42847222 | G6: 0.42561343 | H6: 0.45208333 | I6: 0.47847222 | J6: 0.026469907 | K6: 0.026354167 | L6: =COUNTIFS(Event_Log!$A:$A,A6,Event_Log!$B:$B,">="&G6,Event_Log!$B:$B,"<="&H6) | N6: Arrived 39 min before booking.
A7: 46269 | B7: 5 | C7: Morayfield - general pest | D7: 24769 | E7: 0.52083333 | F7: 0.47847222 | G7: 0.47893519 | H7: 0.52013889 | I7: 0.55763889 | J7: 0.041203704 | K7: 0.037766204 | L7: =COUNTIFS(Event_Log!$A:$A,A7,Event_Log!$B:$B,">="&G7,Event_Log!$B:$B,"<="&H7) | M7: Long leg | N7: Murarrie to Morayfield ~55 km via Gateway / Bruce Hwy. Longest motorway run of the day.
A8: 46269 | B8: 6 | C8: Narangba - 'drop cash' (staff home address) | D8: 24244 | E8: 0.57291667 | F8: 0.55902778 | G8: 0.55881944 | H8: 0.56875 | I8: 0.56944444 | J8: 0.010625 | K8: 0.00038194444 | L8: =COUNTIFS(Event_Log!$A:$A,A8,Event_Log!$B:$B,">="&G8,Event_Log!$B:$B,"<="&H8) | M8: Non-customer stop | N8: 33 seconds on site. Job card title 'ash p', description 'drop cash'. Confirm this errand was authorised and what was dropped.
A9: 46269 | B9: 7 | C9: Murrumba Downs - Termidor HE quote | D9: 24756 | E9: 0.625 | F9: 0.56944444 | G9: 0.5690625 | H9: 0.58125 | I9: 0.60069444 | J9: 0.0121875 | K9: 0.01962963 | L9: =COUNTIFS(Event_Log!$A:$A,A9,Event_Log!$B:$B,">="&G9,Event_Log!$B:$B,"<="&H9) | M9: 63 min early | N9: Booked 15:00, arrived 13:57. Quote $3,969 sent 14:20. Day compressed to finish early.
A10: 46269 | B10: 8 | C10: End of day - return (destination unknown) | G10: 0.60069444 | L10: =COUNTIFS(Event_Log!$A:$A,A10,Event_Log!$B:$B,">="&G10,Event_Log!$B:$B,"<="&TIME(23,59,59)) | M10: Unmatched | N10: Match any Fleeta events after 14:25 to this leg. Trip History will show where the vehicle was parked overnight.
A11: 46270 | B11: 1 | C11: Chapel Hill - St James Estate (follow-up) | D11: 24717 | E11: 0.33333333 | G11: 0.221875 | H11: 0.32400463 | I11: 0.32405093 | J11: 0.10212963 | K11: 4.6296296e-05 | L11: =COUNTIFS(Event_Log!$A:$A,A11,Event_Log!$B:$B,">="&G11,Event_Log!$B:$B,"<="&H11) | M11: PRIORITY | N11: Travel start derived: check-out 07:46:38 minus total 02:27:08. Office to Chapel Hill is ~12 km / 25 min. 2h27m of travel is unexplained. 07:28 call to client lasted 7 s (no answer inferred). Job not performed, still Work Order. Fleeta events 07:03-07:46 fall in this window.
A12: 46270 | B12: 2 | C12: South Brisbane - bed bug inspection/treatment | D12: 24815 | E12: 0.45833333 | F12: 0.32361111 | G12: 0.3241088 | H12: 0.34097222 | I12: 0.34760417 | J12: 0.017118056 | K12: 0.0064351852 | L12: =COUNTIFS(Event_Log!$A:$A,A12,Event_Log!$B:$B,">="&G12,Event_Log!$B:$B,"<="&H12) | M12: Quality | N12: 07:46 called client to come early 'while nearby'. Booked as 1-hour service, on site 9 min, 1 mandatory checklist task skipped at check-out, invoiced $110. Travel from Chapel Hill 25 min is normal.
A13: 46270 | B13: 3 | C13: Parked (Parking Impact 08:34) then off sick | G13: 0.34760417 | L13: =COUNTIFS(Event_Log!$A:$A,A13,Event_Log!$B:$B,">="&G13,Event_Log!$B:$B,"<="&TIME(23,59,59)) | M13: Sick | N13: South Brisbane job is 1.8 km from office. Vehicle parked by 08:34. Jason called the 11:15 client at 11:07: 'technician went home sick'. Job 24831 reassigned to Jason and completed Sun 06/09 08:30.
A15: Totals 04/09 | J15: =SUMIFS(J3:J13,A3:A13,DATE(2026,9,4)) | K15: =SUMIFS(K3:K13,A3:A13,DATE(2026,9,4)) | L15: =SUMIFS(L3:L13,A3:A13,DATE(2026,9,4))
A16: Totals 05/09 | J16: =SUMIFS(J3:J13,A3:A13,DATE(2026,9,5)) | K16: =SUMIFS(K3:K13,A3:A13,DATE(2026,9,5)) | L16: =SUMIFS(L3:L13,A3:A13,DATE(2026,9,5))
A18: Context: Fri 28/08 and Sat 29/08 - no jobs allocated to Javiar (ServiceM8). Fleeta shows zero events both days. Consistent with vehicle not driven.
A19: Travel start is derived (check-out minus total time on the ServiceM8 check-out stamp). ServiceM8 'travel' begins when the tech taps On The Way, so it is a self-reported window, not GPS.

Sheet Event_Log
A1: Enter one row per Fleeta Cloud event. Yellow cells are inputs. Date as dd/mm/yyyy, Time as hh:mm:ss local (confirm Fleeta is showing AEST). Row 4 is the one event already confirmed from the Fleeta calendar view.
A3: Date | B3: Time | C3: Event type | D3: Speed (km/h) | E3: Location / suburb | F3: GPS (lat, long) | G3: Clip file name | H3: Downloaded (Y/N) | I3: SHA-256 | J3: Matched Timeline leg | K3: Audio track (Y/N/Unk) | L3: Reviewed by | M3: Notes
A4: 46270 | B4: 0.35694444 | C4: Parking Impact | H4: N | J4: 05/09 leg 3 | K4: Unk | M4: Seen in Fleeta calendar 06/09. Vehicle parked ~14 min after South Brisbane check-out. Clip not yet downloaded.

Sheet Clip_Register
A1: Chain of custody. One row per file (video clip, SD image, trip export, ServiceM8 diary PDF, call recording). Hash with: certutil -hashfile <file> SHA256 (Windows) or shasum -a 256 <file> (Mac). Never edit originals; work on copies.
A3: Ref | B3: Source | C3: Original file name | D3: Event / content date-time | E3: Collected by | F3: Collected at (date-time) | G3: Stored at (path / drive) | H3: SHA-256 | I3: Copies given to (who, when) | J3: Retention hold until | K3: Notes
A4: EV-001 | B4: Fleeta Cloud | C4: 20260905_083400_PF.mp4 | D4: 05/09/2026 08:34 | E4: J. Cartledge | F4: 07/09/2026 09:00 | G4: SAB-HR\Vehicle-Review-2026-09\clips\ | H4: (paste hash) | I4: - | J4: 05/09/2027 | K4: EXAMPLE ROW - overwrite with the first real clip

Sheet Gaps
A1: # | B1: Gap / question | C1: Why it matters | D1: Owner | E1: Due | F1: Status
A2: 1 | B2: Where was the vehicle 05:19-07:46 on Sat 05/09? | C2: 2h27m of self-reported travel for a 25-min drive, then 4 s on site. Fleeta Trip History answers this. | D2: Browser session | E2: 46272 | F2: Open
A3: 2 | B3: Who is the passenger, what is their role, have they complained? | C3: Decides the process: WHS driving conduct vs harassment complaint (positive duty). Complainant welfare comes first. | D3: Jason | E3: 46272 | F3: Open
A4: 3 | B4: Is cabin audio ON in the camera config? | C4: If ON, recording may breach Invasion of Privacy Act 1971 (Qld) s43. Do not listen or share before legal advice. | D4: Jason | E4: 46272 | F4: Open
A5: 4 | B5: Has Javiar signed a vehicle use / camera monitoring policy? | C5: Notice of monitoring underpins fair use of the footage and any disciplinary reliance on it. | D5: Ashleigh (HR file) | E5: 46272 | F5: Open
A6: 5 | B6: Fleeta Cloud event retention period on the current plan | C6: Sets the hard deadline for downloads. Assume short; download this week regardless. | D6: Browser session | E6: 46272 | F6: Open
A7: 6 | B7: Pull and image the SD card before September overwrites | C7: Card holds continuous footage between triggers for 04-05/09. Cloud does not. | D7: Jason | E7: 46272 | F7: Open
A8: 7 | B8: Was the Narangba 'drop cash' stop (04/09 13:39) authorised, and what was dropped? | C8: Non-customer stop at a staff home on a job card. Needs a one-line explanation on file. | D8: Jason / Ashleigh | E8: 46273 | F8: Open
A9: 8 | B9: Was Javiar rostered on Sat 05/09 and was he told the 08:00 Chapel Hill scope? | C9: Booked 04/09 12:29 by Ashleigh. Confirms expectation vs outcome (job not done). | D9: Ashleigh | E9: 46273 | F9: Open
A10: 9 | B10: Who spoke to Javiar about going home sick on 05/09, at what time? | C10: Fixes the end of the driving window and whether the vehicle moved again that day. | D10: Jason | E10: 46273 | F10: Open
A11: 10 | B11: Is the 'conduct issue' driving behaviour, treatment of the passenger, unauthorised use, or all three? | C11: Each allegation must be put separately and specifically in writing before any meeting. | D11: Jason | E11: 46273 | F11: Open
A12: 11 | B12: Who runs the meeting given the family relationship? | C12: Perceived bias. An external HR adviser or independent manager should conduct and minute it. | D12: Jason | E12: 46274 | F12: Open
A13: 12 | B13: Confirm Fleeta timestamps are AEST and match ServiceM8 | C13: A timezone offset would misalign every event to the wrong leg. | D13: Browser session | E13: 46272 | F13: Open
A14: 13 | B14: Bed bug job 24815: was a 9-minute inspection with a skipped mandatory task acceptable? | C14: Separate service-quality/performance matter. Keep it out of the conduct allegations unless relevant to the day. | D14: Jason | E14: 46274 | F14: Open

Sheet Process
A1: Step | B1: Action | C1: Owner | D1: Due | E1: Done (Y/N) | F1: Evidence / note
A2: Preserve | B2: Pull SD card, image it (full disk image, not file copy), hash, bag and label. Fit new card. | C2: Jason | D2: 46272 | E2: N
A3: Preserve | B3: Fleeta: export Trip History 04/09 and 05/09 (and 28-29/08 to close those out). Screenshot the calendar view. | C3: Browser session | D3: 46272 | E3: N
A4: Preserve | B4: Fleeta: enumerate every event 04/09 and 05/09 into Event_Log. Download all clips, hash each, log in Clip_Register. | C4: Browser session | D4: 46273 | E4: N
A5: Preserve | B5: ServiceM8: export job diaries 24717, 24815, 24831 (05/09) and 24795, 24316, 24654, 24740, 24769, 24244, 24756 (04/09) to PDF. | C5: Ashleigh | D5: 46273 | E5: N
A6: Preserve | B6: Phone system: secure recordings of calls 05/09 07:28 (Gerry) and 07:46 (Charlize) if the system stores audio. | C6: Ashleigh | D6: 46273 | E6: N
A7: Legal | B7: Confirm camera audio setting. If ON: seek legal advice before any use; consider disabling fleet-wide with written notice to staff. | C7: Jason | D7: 46273 | E7: N
A8: Legal | B8: Check HR file for signed vehicle use and monitoring policy. If none, note it and issue one going forward. | C8: Ashleigh | D8: 46273 | E8: N
A9: Scope | B9: Speak with the passenger (welfare first). Record their account. Decide if a formal complaint exists. | C9: Jason (or independent) | D9: 46273 | E9: N
A10: Scope | B10: Write each allegation as a specific, dated statement (what, when, where, which clip). No conclusions. | C10: Independent adviser | D10: 46274 | E10: N
A11: Fairness | B11: Issue written allegations + meeting invite with 24-48 h notice, right to a support person, copies of the clips relied on. | C11: Independent adviser | D11: 46274 | E11: N
A12: Fairness | B12: Hold the meeting. Put each allegation, hear the response, take minutes, adjourn before deciding. | C12: Independent adviser | D12: 46276 | E12: N
A13: Decide | B13: Decide on the evidence and the response. Options: coaching + written warning, final warning, or termination if serious misconduct is made out. | C13: Jason on advice | D13: 46279 | E13: N
A14: Systemise | B14: Fleet safety: telematics scoring review weekly, harsh-event threshold alerts to Jason, driver coaching SOP, passenger authorisation rule. | C14: Jason | D14: 46283 | E14: N
